ate_dispatcher/__init__.py
ate_dispatcher/dispatcher.py
ate_dispatcher/tests/__init__.py
ate_dispatcher/tests/test_dispatcher.py
ate_dispatcher-0.1.0.dist-info/LICENSE
ate_dispatcher-0.1.0.dist-info/METADATA
ate_dispatcher-0.1.0.dist-info/WHEEL
ate_dispatcher-0.1.0.dist-info/top_level.txt
ate_dispatcher-0.1.0.dist-info/RECORD
