Metadata-Version: 2.1
Name: ate-dispatcher
Version: 0.1.0
Summary: Thread-based, asynchronous dispatcher used to gather results from distributed agents.
Home-page: https://github.com/Semi-ATE/ate-dispatcher
Author: Semi-ATE
Author-email: info@Semi-ATE.com
License: MIT
Keywords: ATE,dispatcher,async
Classifier: Development Status :: 5 - Production/Stable
Classifier: Intended Audience :: Developers
Classifier: License :: OSI Approved :: MIT License
Classifier: Programming Language :: Python
License-File: LICENSE
Requires-Dist: typing-extensions
